[[{"__type__":"cc.SceneAsset","_name":"hall","scene":{"__id__":1},"asyncLoadAssets":null},{"__type__":"cc.Scene","_name":"New Node","_children":[{"__id__":2}],"_active":false,"_anchorPoint":{"__type__":"cc.Vec2"},"_scale":{"__type__":"cc.Vec3","x":0.5623618194946831,"y":0.5623618194946831,"z":1},"autoReleaseAssets":false},{"__type__":"cc.Node","_name":"Canvas","_parent":{"__id__":1},"_children":[{"__id__":3},{"__id__":4},{"__id__":6},{"__id__":9}],"_level":1,"_components":[{"__type__":"cc.Canvas","node":{"__id__":2},"_designResolution":{"__type__":"cc.Size","width":1280,"height":720}},{"__type__":"49cddjhR3ZCxIlwFDavBgF7","node":{"__id__":2},"rolePanel":{"__uuid__":"cdlDue45xLJKP0TYxB4Ozz"}}],"_contentSize":{"__type__":"cc.Size","width":1280,"height":720},"_position":{"__type__":"cc.Vec3","x":640,"y":360},"_id":"4fM4DugARJg7nlo33HfMS5"},{"__type__":"cc.Node","_name":"Main Camera","_parent":{"__id__":2},"_level":1,"_components":[{"__type__":"cc.Camera","node":{"__id__":3},"_clearFlags":7,"_depth":-1}]},{"__type__":"cc.Node","_name":"BGmask","_parent":{"__id__":2},"_children":[{"__id__":5}],"_level":1,"_components":[{"__type__":"cc.Mask","node":{"__id__":4}},{"__type__":"cc.Widget","node":{"__id__":4},"_target":{"__id__":2},"_alignFlags":45}],"_contentSize":{"__type__":"cc.Size","width":1280,"height":720}},{"__type__":"cc.Node","_name":"bg","_parent":{"__id__":4},"_level":2,"_components":[{"__type__":"cc.Sprite","node":{"__id__":5},"_spriteFrame":{"__uuid__":"c2FU+nATJJ87DaIMdDTU+F"}}],"_contentSize":{"__type__":"cc.Size","width":1280,"height":720}},{"__type__":"cc.Node","_name":"rightMenu","_parent":{"__id__":2},"_children":[{"__id__":7}],"_level":2,"_components":[{"__type__":"cc.Widget","node":{"__id__":6},"_alignFlags":37}],"_contentSize":{"__type__":"cc.Size","width":180,"height":720},"_position":{"__type__":"cc.Vec3","x":550}},{"__type__":"cc.Node","_name":"title","_parent":{"__id__":6},"_children":[{"__id__":8}],"_level":3,"_components":[{"__type__":"cc.Sprite","node":{"__id__":7},"_spriteFrame":{"__uuid__":"d8YResnOBEoZwmwzysl5cj"}},{"__type__":"cc.Button","node":{"__id__":7},"clickEvents":[{"__type__":"cc.ClickEvent","target":{"__id__":2},"_componentId":"49cddjhR3ZCxIlwFDavBgF7","handler":"clickPlayBtn"}],"_N$transition":3,"transition":3,"_N$normalColor":{"__type__":"cc.Color","r":214,"g":214,"b":214}}],"_contentSize":{"__type__":"cc.Size","width":195,"height":60},"_position":{"__type__":"cc.Vec3","x":-57,"y":-245}},{"__type__":"cc.Node","_name":"lb","_parent":{"__id__":7},"_level":4,"_components":[{"__type__":"cc.Label","node":{"__id__":8},"_useOriginalSize":false,"_string":"P L A Y","_N$string":"P L A Y","_fontSize":36,"_N$file":{"__uuid__":"a5cjCOOJZHxpwMiUobMqbU"},"_isSystemFontUsed":false,"_N$horizontalAlign":1,"_N$verticalAlign":1},{"__type__":"cc.LabelOutline","node":{"__id__":8},"_color":{"__type__":"cc.Color","r":214,"g":233},"_width":2}],"_color":{"__type__":"cc.Color","r":255},"_contentSize":{"__type__":"cc.Size","width":103,"height":40},"_position":{"__type__":"cc.Vec3","x":-1.3,"y":-4.6}},{"__type__":"cc.Node","_name":"leftMenu","_parent":{"__id__":2},"_children":[{"__id__":10}],"_level":2,"_components":[{"__type__":"cc.Widget","node":{"__id__":9},"_alignFlags":13,"_originalWidth":180}],"_contentSize":{"__type__":"cc.Size","width":180,"height":720},"_position":{"__type__":"cc.Vec3","x":-550}},{"__type__":"cc.Node","_name":"btn_back","_parent":{"__id__":9},"_level":3,"_components":[{"__type__":"cc.Sprite","node":{"__id__":10},"_spriteFrame":{"__uuid__":"c41rDgLN1Lu63bbRWJNgEf"}}],"_contentSize":{"__type__":"cc.Size","width":78,"height":61},"_position":{"__type__":"cc.Vec3","x":-23,"y":301}}],{"__type__":"cc.SpriteFrame","content":{"name":"bg","texture":"a99X4szFdLR5HakK+5qfnw","rect":[0,0,1280,720],"offset":[0,0],"originalSize":[1280,720],"capInsets":[0,0,0,0]}},{"__type__":"cc.SpriteFrame","content":{"name":"btn_back","texture":"a91fVSJZtGVLYYF0JGFODD","rect":[4,5,78,61],"offset":[-1.5,0],"originalSize":[89,71],"capInsets":[0,0,0,0]}},{"__type__":"cc.SpriteFrame","content":{"name":"title","texture":"52sEs3Pu5O1oE7wYyoYg1q","rect":[938,670,195,60],"offset":[0,0],"originalSize":[195,60],"rotated":1,"capInsets":[0,0,0,0]}}]